README.txt
setup.cfg
setup.py
docs/HISTORY.txt
docs/INSTALL.txt
docs/LICENSE.GPL
docs/LICENSE.txt
easyshop/__init__.py
easyshop.management.egg-info/PKG-INFO
easyshop.management.egg-info/SOURCES.txt
easyshop.management.egg-info/dependency_links.txt
easyshop.management.egg-info/entry_points.txt
easyshop.management.egg-info/namespace_packages.txt
easyshop.management.egg-info/not-zip-safe
easyshop.management.egg-info/requires.txt
easyshop.management.egg-info/top_level.txt
easyshop/management/__init__.py
easyshop/management/configure.zcml
easyshop/management/interfaces.py
easyshop/management/tests.py
easyshop/management/adapters/__init__.py
easyshop/management/ajax/__init__.py
easyshop/management/ajax/configure.zcml
easyshop/management/ajax/manage_categories.py
easyshop/management/browser/__init__.py
easyshop/management/browser/category_manage_products.pt
easyshop/management/browser/category_manage_products.py
easyshop/management/browser/configure.zcml
easyshop/management/browser/manage_categories.pt
easyshop/management/browser/manage_categories.py
easyshop/management/browser/manage_products.pt
easyshop/management/browser/manage_products.py
easyshop/management/browser/manage_redirections.pt
easyshop/management/browser/manage_redirections.py
easyshop/management/profiles/default/cssregistry.xml
easyshop/management/profiles/default/kssregistry.xml
easyshop/management/profiles/default/skins.xml
easyshop/management/profiles/default/viewlets.xml
easyshop/management/scripts/__init__.py
easyshop/management/scripts/configure.zcml
easyshop/management/scripts/manage_sessions.py
easyshop/management/skins/easyshop.management/categories_macros.pt
easyshop/management/skins/easyshop.management/easyshop.management.css.dtml
easyshop/management/skins/easyshop.management/selected_category_icon.png
easyshop/management/viewlets/__init__.py
easyshop/management/viewlets/actions.pt
easyshop/management/viewlets/actions.py
easyshop/management/viewlets/categories.pt
easyshop/management/viewlets/categories.py
easyshop/management/viewlets/configure.zcml
easyshop/management/viewlets/select_products.pt
easyshop/management/viewlets/select_products.py