Metadata-Version: 1.0
Name: easyshop.management
Version: 0.1a1
Summary: Management screens for EasyShop
Home-page: http://svn.plone.org/svn/plone/plone.example
Author: Plone Foundation
Author-email: plone-developers@lists.sourceforge.net
License: GPL
Platform: UNKNOWN
Classifier: Framework :: Plone
Classifier: Framework :: Zope2
Classifier: Framework :: Zope3
Classifier: Programming Language :: Python
Classifier: Topic :: Software Development :: Libraries :: Python Modules
